gsheet_loader/__init__.py
gsheet_loader/loader.py
gsheet_loader-1.0.2.dist-info/METADATA
gsheet_loader-1.0.2.dist-info/WHEEL
gsheet_loader-1.0.2.dist-info/top_level.txt
gsheet_loader-1.0.2.dist-info/RECORD
