Metadata-Version: 2.4
Name: gsheet-loader
Version: 1.0.2
Summary: A simple package to load Google Sheets into pandas DataFrame
Home-page: https://github.com/arshadziban/gsheet_loader
Author: Arshad Ziban
Author-email: Arshad Ziban <arshadziban031201@gmail.com>
Project-URL: Homepage, https://github.com/arshadziban/gsheet_loader
Project-URL: Repository, https://github.com/arshadziban/gsheet_loader
Keywords: google sheets,pandas,dataframe,csv,data loading
Classifier: Development Status :: 4 - Beta
Classifier: Intended Audience :: Developers
Classifier: Intended Audience :: Science/Research
Classifier: Operating System :: OS Independent
Classifier: Programming Language :: Python :: 3
Classifier: Programming Language :: Python :: 3.7
Classifier: Programming Language :: Python :: 3.8
Classifier: Programming Language :: Python :: 3.9
Classifier: Programming Language :: Python :: 3.10
Classifier: Programming Language :: Python :: 3.11
Classifier: Programming Language :: Python :: 3.12
Requires-Python: >=3.7
Requires-Dist: pandas
Requires-Dist: requests
Dynamic: author
Dynamic: home-page
Dynamic: requires-python
